{"users":[{"password":"12345","firstname":"Casper","portfolio":[{"ticker":"gme","price":179.8506,"count":9040},{"ticker":"amc","price":58.244446,"count":180}],"cash":19008.09,"age":20,"username":"casper","lastname":"Amtrup"},{"password":"123","firstname":"Karano","portfolio":[{"ticker":"AAPL","price":148.57875,"count":16},{"ticker":"GME","price":170.99,"count":5},{"ticker":"TSLA","price":929.915,"count":4},{"ticker":"MMM","price":179.91,"count":10},{"ticker":"BRO","price":66.960144,"count":69},{"ticker":"AAPl","price":148.88,"count":4}],"cash":20000.0,"age":20,"username":"karan","lastname":"Singh"},{"password":"123","firstname":"Karano","portfolio":[{"ticker":"AAPL","price":148.46,"count":11},{"ticker":"GME","price":170.99,"count":5},{"ticker":"TSLA","price":909.25,"count":3},{"ticker":"gme","price":172.28,"count":1}],"cash":20000.0,"age":20,"username":"karan","lastname":"Singh"},{"password":"test","firstname":"test","portfolio":[],"cash":1.0E10,"age":20,"username":"test","lastname":"test"},{"password":"test","firstname":"test","portfolio":[],"cash":10000.0,"age":20,"username":"test2","lastname":"test"}]}