[{"firstName":"casper","lastName":"amtrup","password":"c4ca4238a0b923820dcc509a6f75849b","portfolio":[{"priceChange":"-0.02%","ticker":"gme","price":206.55,"name":"GameStop Corp. Cl A","count":1}],"watchList":[],"cash":1.0E10,"age":20,"username":"casper"},{"firstName":"torstein","lastName":"olsen","password":"d141f75795c7d7a224c0423ebd221dc7","portfolio":[{"priceChange":"1.12%","ticker":"gme","price":201.43,"name":"GameStop Corp. Cl A","count":1},{"priceChange":"0.18%","ticker":"spx","price":4655.02,"name":"S&P 500 Index","count":1}],"watchList":[],"cash":104856.45,"age":20,"username":"olsen"}]